setup.py
baidumap/README.md
baidumap/__init__.py
baidumap/config.py
baidumap/object.py
baidumap.egg-info/PKG-INFO
baidumap.egg-info/SOURCES.txt
baidumap.egg-info/dependency_links.txt
baidumap.egg-info/requires.txt
baidumap.egg-info/top_level.txt
baidumap/api/__init__.py
baidumap/api/exceptions.py
baidumap/api/handle.py
baidumap/core/__init__.py
baidumap/core/collector.py
baidumap/core/controller.py
baidumap/core/static.py
baidumap/core/status.py
baidumap/util/__init__.py
baidumap/util/dict_tool.py
baidumap/util/list_tool.py
baidumap/util/log.py
baidumap/util/url.py