Metadata-Version: 2.1
Name: baidumap
Version: 1.2.4
Summary: api handle for baidu map
Home-page: https://github.com/cpak00/baidumap
Author: chenyiming
Author-email: cymcpak00@gmail.com
License: MIT Licence
Keywords: baidu,map,api,web
Platform: any
